{"deployments":{"text-green":{"vsn":"preview","compu_level":2,"comm_level":2,"dp_acc":"acc_none","intlmodule":"edge"},"hat-red":{"vsn":"development","compu_level":1,"comm_level":2,"dp_acc":"acc_none","intlmodule":"edge"}},"devices":{"RaspberryPi6":{"environment":"safe-mode","status":"running","capability":"sensehat","range":"9","cpu":"1400","storage":"8","ram":"512"},"RaspberryPi3":{"environment":"safe-mode","status":"running","capability":"sensehat","range":"5","cpu":"1400","storage":"16","ram":"1024"},"RaspberryPi7":{"environment":"safe-mode","status":"running","capability":"sensehat","range":"12","cpu":"700","storage":"8","ram":"256","network":"4g"},"RaspberryPi1":{"environment":"safe-mode","status":"running","capability":"sensehat","range":"5","cpu":"700","storage":"4","ram":"256"},"dv0":{"env":"production","dv_acc":"acc_none","network":"4g","powersource":"ac"},"RaspberryPi5":{"environment":"safe-mode","status":"running","capability":"sensehat","range":"15","cpu":"900","storage":"8","ram":"256"}}}